{"commitInfo":{"timestamp":1759663697820,"userId":"145671062717390","userName":"dilinikeshanir@gmail.com","operation":"RESTORE","operationParameters":{"version":0,"timestamp":null},"notebook":{"notebookId":"3914563296253205"},"clusterId":"1005-095602-3yqeuv8t","readVersion":3,"isolationLevel":"Serializable","isBlindAppend":false,"operationMetrics":{"numRestoredFiles":"1","removedFilesSize":"10044","numRemovedFiles":"1","restoredFilesSize":"10044","numOfFilesAfterRestore":"1","tableSizeAfterRestore":"10044"},"engineInfo":"Databricks-Runtime/14.3.x-scala2.12","txnId":"2736e9dd-4b68-4a39-b2cf-7da33737bfac"}}
{"metaData":{"id":"59ff53b0-9972-4852-916a-9045b16c0e11","format":{"provider":"parquet","options":{}},"schemaString":"{\"type\":\"struct\",\"fields\":[{\"name\":\"LocationID\",\"type\":\"integer\",\"nullable\":true,\"metadata\":{}},{\"name\":\"Borough\",\"type\":\"string\",\"nullable\":true,\"metadata\":{}},{\"name\":\"Zone\",\"type\":\"string\",\"nullable\":true,\"metadata\":{}},{\"name\":\"service_zone\",\"type\":\"string\",\"nullable\":true,\"metadata\":{}},{\"name\":\"zone1\",\"type\":\"string\",\"nullable\":true,\"metadata\":{}},{\"name\":\"zone2\",\"type\":\"string\",\"nullable\":true,\"metadata\":{}}]}","partitionColumns":[],"configuration":{"delta.enableDeletionVectors":"true"},"createdTime":1759662658578}}
{"protocol":{"minReaderVersion":3,"minWriterVersion":7,"readerFeatures":["deletionVectors"],"writerFeatures":["deletionVectors"]}}
{"remove":{"path":"part-00000-652b186a-b969-4e17-ba40-03db1f0024b5-c000.snappy.parquet","deletionTimestamp":1759663696005,"dataChange":true,"extendedFileMetadata":true,"partitionValues":{},"size":10044,"tags":{"INSERTION_TIME":"1759662659000000","MIN_INSERTION_TIME":"1759662659000000","MAX_INSERTION_TIME":"1759662659000000","OPTIMIZE_TARGET_SIZE":"268435456"},"deletionVector":{"storageType":"u","pathOrInlineDv":"Bdl81DqN1%I}9ZyNJNTz","offset":1,"sizeInBytes":34,"cardinality":1},"stats":"{\"numRecords\":265,\"minValues\":{\"LocationID\":1,\"Borough\":\"Bronx\",\"Zone\":\"Allerton/Pelham Gardens\",\"service_zone\":\"Airports\",\"zone1\":\"Allerton\",\"zone2\":\"A\"},\"maxValues\":{\"LocationID\":265,\"Borough\":\"Unknown\",\"Zone\":\"Yorkville West\",\"service_zone\":\"Yellow Zone\",\"zone1\":\"Yorkville West\",\"zone2\":\"Woodside\"},\"nullCount\":{\"LocationID\":0,\"Borough\":0,\"Zone\":0,\"service_zone\":0,\"zone1\":0,\"zone2\":206},\"tightBounds\":false}"}}
{"add":{"path":"part-00000-652b186a-b969-4e17-ba40-03db1f0024b5-c000.snappy.parquet","partitionValues":{},"size":10044,"modificationTime":1759662659000,"dataChange":true,"stats":"{\"numRecords\":265,\"minValues\":{\"LocationID\":1,\"Borough\":\"Bronx\",\"Zone\":\"Allerton/Pelham Gardens\",\"service_zone\":\"Airports\",\"zone1\":\"Allerton\",\"zone2\":\"A\"},\"maxValues\":{\"LocationID\":265,\"Borough\":\"Unknown\",\"Zone\":\"Yorkville West\",\"service_zone\":\"Yellow Zone\",\"zone1\":\"Yorkville West\",\"zone2\":\"Woodside\"},\"nullCount\":{\"LocationID\":0,\"Borough\":0,\"Zone\":0,\"service_zone\":0,\"zone1\":0,\"zone2\":206},\"tightBounds\":true}","tags":{"INSERTION_TIME":"1759662659000000","MIN_INSERTION_TIME":"1759662659000000","MAX_INSERTION_TIME":"1759662659000000","OPTIMIZE_TARGET_SIZE":"268435456"}}}
